selva-0.19.4.dist-info/METADATA
selva-0.19.4.dist-info/WHEEL
selva-0.19.4.dist-info/entry_points.txt
selva-0.19.4.dist-info/licenses/LICENSE
selva/__init__.py
selva/__version__.py
selva/_util/__init__.py
selva/_util/base_types.py
selva/_util/dotenv.py
selva/_util/import_item.py
selva/_util/maybe_async.py
selva/_util/package_scan.py
selva/_util/pydantic/__init__.py
selva/_util/pydantic/dotted_path.py
selva/configuration/__init__.py
selva/configuration/defaults.py
selva/configuration/environment.py
selva/configuration/settings.py
selva/di/__init__.py
selva/di/call.py
selva/di/container.py
selva/di/decorator.py
selva/di/error.py
selva/di/inject.py
selva/di/interceptor.py
selva/di/service/__init__.py
selva/di/service/model.py
selva/di/service/parse.py
selva/di/service/registry.py
selva/ext/__init__.py
selva/ext/data/__init__.py
selva/ext/data/memcached/__init__.py
selva/ext/data/memcached/service.py
selva/ext/data/memcached/settings.py
selva/ext/data/redis/__init__.py
selva/ext/data/redis/service.py
selva/ext/data/redis/settings.py
selva/ext/data/sqlalchemy/__init__.py
selva/ext/data/sqlalchemy/middleware.py
selva/ext/data/sqlalchemy/service.py
selva/ext/data/sqlalchemy/settings.py
selva/ext/error.py
selva/ext/templates/__init__.py
selva/ext/templates/jinja/__init__.py
selva/ext/templates/jinja/service.py
selva/ext/templates/jinja/settings.py
selva/ext/templates/mako/__init__.py
selva/ext/templates/mako/service.py
selva/ext/templates/mako/settings.py
selva/logging.py
selva/py.typed
selva/run.py
selva/web/__init__.py
selva/web/application.py
selva/web/converter/__init__.py
selva/web/converter/converter.py
selva/web/converter/converter_impl.py
selva/web/converter/decorator.py
selva/web/converter/error.py
selva/web/converter/from_request.py
selva/web/converter/from_request_impl.py
selva/web/converter/param_converter_impl.py
selva/web/converter/param_extractor.py
selva/web/converter/param_extractor_impl.py
selva/web/exception.py
selva/web/exception_handler/__init__.py
selva/web/exception_handler/decorator.py
selva/web/exception_handler/discover.py
selva/web/handler/__init__.py
selva/web/handler/call.py
selva-0.19.4.dist-info/RECORD
